autoblockchainify/__init__.py
autoblockchainify/commit.py
autoblockchainify/config.py
autoblockchainify/daemon.py
autoblockchainify/deltat.py
autoblockchainify/mail.py
autoblockchainify/version.py
zeitgitter/__init__.py
zeitgitter/commit.py
zeitgitter/config.py
zeitgitter/deltat.py
zeitgitter/mail.py
zeitgitter/sample.conf
zeitgitter/server.py
zeitgitter/stamper.py
zeitgitter/version.py
zeitgitter/web/README.md
zeitgitter/web/contact.html
zeitgitter/web/favicon.ico
zeitgitter/web/index.html
zeitgitter/web/privacy.html
zeitgitter/web/robots.txt
zeitgitter/web/sitemap.xml
zeitgitter/web/tos.html
zeitgitter/web/zeitgitter.css
zeitgitter/web/zeitgitter.svg
zeitgitter/web/zg-icon.svg
zeitgitter/web/zg-white.svg
zeitgitterd-1.2.0.dist-info/LICENSE.md
zeitgitterd-1.2.0.dist-info/METADATA
zeitgitterd-1.2.0.dist-info/WHEEL
zeitgitterd-1.2.0.dist-info/entry_points.txt
zeitgitterd-1.2.0.dist-info/top_level.txt
zeitgitterd-1.2.0.dist-info/RECORD
