Metadata-Version: 2.1
Name: zeitgitterd
Version: 1.2.0
Summary: Zeitgitter timestamping server
Home-page: https://gitlab.com/zeitgitter/zeitgitterd
Author: Marcel Waldvogel
Author-email: marcel.waldvogel@trifence.ch
License: AGPLv3
Classifier: Development Status :: 4 - Beta
Classifier: Environment :: No Input/Output (Daemon)
Classifier: Intended Audience :: Information Technology
Classifier: Programming Language :: Python
Classifier: License :: OSI Approved :: GNU Affero General Public License v3
Classifier: Operating System :: OS Independent
Classifier: Natural Language :: English
Classifier: Topic :: Software Development :: Version Control :: Git
Classifier: Topic :: Security
Requires-Python: >=3.7
License-File: LICENSE.md
Requires-Dist: configargparse
Requires-Dist: git-timestamp
Requires-Dist: pygit2
Requires-Dist: python-gnupg
Requires-Dist: requests
Requires-Dist: setuptools
